{
  "type": "GenericCrafter",
  "name": "Cryo mixer",
  "description": "смешивает воду, титан и бутылки криожидкости в большое количество этой самой жидкости",
  "health": 400,
  "size": 3,
  "requirements": [
    { "item": "cryo-bottle", "amount": 350},
	{ "item": "metaglass", "amount": 200},
	{ "item": "silicon", "amount": 300},
	{ "item": "graphite", "amount": 350}
  ],
  "research": "alloy-smelter",
  "hasPower": true,
  "hasItems": true,
  "hasLiquids": true,
  "craftTime": 40,
"consumes": {
    "power": 6,
    "items": {
      "items": [
        { "item": "titanium", "amount": 3 }
		{ "item": "cryo-bottle", "amount": 1}
      ]
    },
    "liquids": [
      { "liquid": "water", "amount": 0.15}
	]
  },
  "updateEffect": "smeltsmoke",
  "craftEffect": "smeltsmoke",
  "idleSound": "respawning",
  "idleSoundVolume": 3,
  "itemCapacity": 70,
  "category": "crafting"
  "outputLiquids": [
    {
      "liquid": "cryofluid",
      "amount": 0.6
    }
  ],
}
